__init__.py
test.py
train.py
_tests/__init__.py
_tests/test_center_crops.py
criterions/__init__.py
criterions/lovasz_losses.py
criterions/my_loss.py
criterions/my_loss_3d.py
datasets/ThreeDimensionalDataset.py
datasets/TwoDimensionalDataset.py
datasets/__init__.py
models/BranchedERFNet.py
models/BranchedERFNet_3d.py
models/__init__.py
models/erfnet.py
models/erfnet_3d.py
utils/__init__.py
utils/create_dicts.py
utils/generate_crops.py
utils/glasbey.py
utils/metrics.py
utils/preprocess_data.py
utils/test_time_augmentation.py
utils/transforms.py
utils/utils.py
utils/view_palette.py
utils/visualize.py
embedseg-0.2.5.dist-info/METADATA
embedseg-0.2.5.dist-info/WHEEL
embedseg-0.2.5.dist-info/licenses/LICENSE
embedseg-0.2.5.dist-info/RECORD
