Metadata-Version: 2.1
Name: EmbedSeg
Version: 0.2.5
Summary: EmbedSeg provides automatic detection and segmentation of objects in microscopy images
Project-URL: homepage, https://github.com/juglab/EmbedSeg/
Project-URL: repository, https://github.com/juglab/EmbedSeg/
Author: Pavel Tomancak, Florian Jug
Author-email: Manan Lalit <lalitm@janelia.hhmi.org>
License: BSD-3-Clause
License-File: LICENSE
Classifier: License :: OSI Approved :: BSD License
Classifier: Programming Language :: Python :: 3
Classifier: Programming Language :: Python :: 3.8
Classifier: Programming Language :: Python :: 3.9
Classifier: Programming Language :: Python :: 3.10
Classifier: Programming Language :: Python :: 3.11
Requires-Python: >=3.8
Requires-Dist: colorspacious
Requires-Dist: jupyter
Requires-Dist: matplotlib
Requires-Dist: numba
Requires-Dist: numpy
Requires-Dist: pandas
Requires-Dist: pycocotools
Requires-Dist: scikit-image
Requires-Dist: scipy
Requires-Dist: seaborn
Requires-Dist: tifffile
Requires-Dist: tqdm
Provides-Extra: test
Requires-Dist: pytest; extra == 'test'
Requires-Dist: pytest-cov; extra == 'test'
